
[
  {
    "id": 0,
    "category": "Eletrodomésticos",
    "photo_main": "assets/id_0/photo_main.png",
    "title": "Difusor de aromaterapia 2 em 1 Umidificador difusor de óleo essencial com luz noturna de chama", 
    "featured": false,
    "url": "https://amzn.to/3FWUskq"
  },
  {
    "id": 1,
    "category": "Cozinha",
    "photo_main": "assets/id_1/photo_main.png",
    "title": "Abridor de vinho elétrico, Saca-rolhas de vinho reutilizável com cortador de lacre",
    "featured": true,
    "url": "https://amzn.to/3FVqRaQ"
  },
  {
    "id": 2,
    "category": "Eletrodomésticos",
    "photo_main": "assets/id_2/photo_main.png",
    "title": "Chaleira Elétrica, 1,7L, Prata, 110v, Hamilton Beach",
    "featured": false,
    "url": "https://amzn.to/49y7guX"
  },
  {
    "id": 3,
    "category": "Eletrodomésticos",
    "photo_main": "assets/id_3/photo_main.png",
    "title": "Torradeira Oster 127V - OTOR650, Modelo: OTOR650-127V",
    "featured": true,
    "url": "https://amzn.to/47o2uhC"
  },
  {
    "id": 4,
    "category": "Eletrodomésticos",
    "photo_main": "assets/id_4/photo_main.png",
    "title": "Umidificador de Ar Luminária com Difusor de Aromas, Aromatizador de Ambientes",
    "featured": false,
    "url": "https://amzn.to/47xnmDr"
  },
  {
    "id": 5,
    "category": "Eletrodomésticos",
    "photo_main": "assets/id_5/photo_main.png",
    "title": "Aspirador de Pó Robô Mars Varre + Aspira + Passa Pano",
    "featured": false,
    "url": "https://amzn.to/3u70Pi9"
  },
  {
    "id": 6,
    "category": "Banheiro",
    "photo_main": "assets/id_6/photo_main.png",
    "title": "Conjunto de Banheiro Lunar com 3 itens, Porta Sabonete Líquido, Porta Escova e Saboneteira",
    "featured": false,
    "url": "https://amzn.to/478GsQu"
  },
  {
    "id": 7,
    "category": "Decoração",
    "photo_main": "assets/id_7/photo_main.png",
    "title": "Espelho Orgânico - Couro - 60x80cm",
    "featured": false,
    "url": "https://amzn.to/3QD228H"
  },
  {
    "id": 8,
    "category": "Cozinha",
    "photo_main": "assets/id_8/photo_main.png",
    "title": "Porta Xícaras de Chá, Rosé Gold",
    "featured": false,
    "url": "https://amzn.to/3FVsaqg"
  },
 {
    "id": 9,
    "category": "Eletrodomésticos",
    "photo_main": "assets/id_9/photo_main.png",
    "title": "Cafeteira Francesa",
    "featured": false,
    "url": "https://amzn.to/3sn5JHB"
  },
 {
    "id": 10,
    "category": "Cozinha",
    "photo_main": "assets/id_10/photo_main.png",
    "title": "Bandeja Cantinho do Café",
    "featured": false,
    "url": "https://amzn.to/465OiJ7"
  },
 {
    "id": 11,
    "category": "Móveis",
    "photo_main": "assets/id_11/photo_main.png",
    "title": "Mesa de Apoio e Mesa Lateral",
    "featured": false,
    "url": "https://amzn.to/40xs15O"
  },
 {
    "id": 12,
    "category": "Cozinha",
    "photo_main": "assets/id_12/photo_main.png",
    "title": "Jogo de 3 Pçs Bowls de Bambu Ecológico",
    "featured": false,
    "url": "https://amzn.to/40ASdMZ"
  },
  {
    "id": 13,
    "category": "Decoração",
    "photo_main": "assets/id_13/photo_main.png",
    "title": "Quadros Decorativos Cantinho do Café",
    "featured": false,
    "url": "https://amzn.to/3ubzsDI"
  },
 {
    "id": 14,
    "category": "Cozinha",
    "photo_main": "assets/id_14/photo_main.png",
    "title": "Potes Herméticos Porta-Mantimentos com Tampa de Bambu Electrolux - 4 unidades",
    "featured": false,
    "url": "https://amzn.to/49zJIWs"
  },
 {
    "id": 15,
    "category": "Móveis",
    "photo_main": "assets/id_15/photo_main.png",
    "title": "Aparador Buffet Retrô 2 Portas Ripado 3D Luxo",
    "featured": false,
    "url": "https://amzn.to/40za5I2"
 },
 {
    "id": 16,
    "category": "Decoração",
    "photo_main": "assets/id_16/photo_main.png",
    "title": "Kit 2 Prateleiras de Madeira Maciça Pinus 40x15cm com alça Caramelo",
    "featured": false,
    "url": "https://amzn.to/3SAAcwe"
  },
  {
    "id": 17,
    "category": "Decoração",
    "photo_main": "assets/id_17/photo_main.png",
    "title": "Luminaria 3D Touch Lua Cheia Abajur LED",
    "featured": false,
    "url": "https://amzn.to/3sxs1Gz"
  },
  {
    "id": 18,
    "category": "Decoração",
    "photo_main": "assets/id_18/photo_main.png",
    "title": "Quadros Decorativos Minimalista Orgânico Floral Moderno",
    "featured": false,
    "url": "https://amzn.to/3QUVBPy"
  },
  {
    "id": 19,
    "category": "Decoração",
    "photo_main": "assets/id_19/photo_main.png",
    "title": "Vaso Cachepot de Mesa 25cm Porcelana com Tripé de Madeira",
    "featured": false,
    "url": "https://amzn.to/3QTUMGB"
  },
  {
    "id": 20,
    "category": "Decoração",
    "photo_main": "assets/id_20/photo_main.png",
    "title": "Kit 4 Capas de Almofadas Decorativas 45x45",
    "featured": false,
    "url": "https://amzn.to/46d6kZY"
  },
  {
    "id": 21,
    "category": "Decoração",
    "photo_main": "assets/id_21/photo_main.png",
    "title": "Puff Em Couro e Linho Pés Madeira Maciça 42x32",
    "featured": false,
    "url": "https://amzn.to/3MC3JSo"
  },
  {
    "id": 22,
    "category": "Eletrodomésticos",
    "photo_main": "assets/id_22/photo_main.png",
    "title": "Ventilador de Mesa Desmontável Arno Xtreme Force Breeze 40cm ",
    "featured": false,
    "url": "https://amzn.to/4765kIx"
  },
  {
    "id": 23,
    "category": "Eletrodomésticos",
    "photo_main": "assets/id_23/photo_main.png",
    "title": "Ventilador de Coluna, Air Timer Style TS+, Preto/Branco,Mallory",
    "featured": false,
    "url": "https://amzn.to/3sqch8o"
  },
  {
    "id": 24,
    "category": "Eletrodomésticos",
    "photo_main": "assets/id_24/photo_main.png",
    "title": "Mop com balde e esfregão giro",
    "featured": false,
    "url": "https://amzn.to/3QXo6Mu"
  },
  {
    "id": 25,
    "category": "Eletrodomésticos",
    "photo_main": "assets/id_25/photo_main.png",
    "title": "Suggar Depurador de ar Slim 60cm 3 Vel. Preto",
    "featured": false,
    "url": "https://amzn.to/3srrPc1"
  },
  {
    "id": 26,
    "category": "Eletrodomésticos",
    "photo_main": "assets/id_26/photo_main.png",
    "title": "Cooktop a Gás Mondial, 4 Bocas, Bivolt, Preto/Inox",
    "featured": false,
    "url": "https://amzn.to/3MMpuz3"
  },
  {
    "id": 27,
    "category": "Eletrodomésticos",
    "photo_main": "assets/id_27/photo_main.png",
    "title": "Climatizador de Ar, Liva, Frio, 220V",
    "featured": false,
    "url": "https://amzn.to/479E77M"
  },
  {
    "id": 28,
    "category": "Eletrodomésticos",
    "photo_main": "assets/id_28/photo_main.png",
    "title": "Ventilador de Teto, Fênix 370, Branco, 127V",
    "featured": false,
    "url": "https://amzn.to/46j8h7c"
  },
  {
    "id": 29,
    "category": "Eletrodomésticos",
    "photo_main": "assets/id_29/photo_main.png",
    "title": "Cervejeira Consul Titanium",
    "featured": false,
    "url": "https://amzn.to/47ubUIy"
  },
  {
    "id": 30,
    "category": "Eletrodomésticos",
    "photo_main": "assets/id_30/photo_main.png",
    "title": "Frigobar, 45L, 127 V, Branco",
    "featured": false,
    "url": "https://amzn.to/40MqlWs"
  },
  {
    "id": 31,
    "category": "Eletrodomésticos",
    "photo_main": "assets/id_31/photo_main.png",
    "title": "Gerador De Energia Solar, Painel Solar Portátil De 9W, Porta Usb Com Iluminação De Lâmpada",
    "featured": false,
    "url": "https://amzn.to/46mHYgo"
  },
  {
    "id": 32,
    "category": "Eletrodomésticos",
    "photo_main": "assets/id_32/photo_main.png",
    "title": "Gerador solar portátil da estação de energia 600W(pico de 1200 W), 568Wh ao ar livre gerador solar móvel bateria de lítio com painel solar 100W para RV Road Trip Camping",
    "featured": false,
    "url": "https://amzn.to/3MRi2Th"
  },
  {
    "id": 33,
    "category": "Eletrodomésticos",
    "photo_main": "assets/id_33/photo_main.png",
    "title": "Painel Solar Portátil Carregador de Telefone para Android Smartphones Tablets Android Painel Solar Dobrável para Acampar Ao Ar Livre",
    "featured": false,
    "url": "https://amzn.to/47Hh4kO"
  },
  {
    "id": 34,
    "category": "Eletrodomésticos",
    "photo_main": "assets/id_34/photo_main.png",
    "title": "Mini Liquidificador Portátil Shake 6 Laminas + Cabo USB",
    "featured": false,
    "url": "https://shope.ee/508wmFLLCQ"
  },
  {
    "id": 35,
    "category": "Cozinha",
    "photo_main": "assets/id_35/photo_main.png",
    "title": "Cafeteira Italiana Alumínio Premium 3 6 9 Xícaras Moka Café Expresso",
    "featured": false,
    "url": "https://shope.ee/4AZploC0OR"
  },
  {
    "id": 36,
    "category": "Eletrodomésticos",
    "photo_main": "assets/id_36/photo_main.png",
    "title": "Kindle 11ª Geração (lançamento 2022). Mais leve, com resolução de 300 ppi e o dobro de armazenamento",
    "featured": false,
    "url": "https://amzn.to/3GHORPi"
  },
  {
    "id": 37,
    "category": "Eletrodomésticos",
    "photo_main": "assets/id_37/photo_main.png",
    "title": "Celular Xiaomi Redmi Note 12 256/8GB 128/8GB. 6GB ou 4GB Ram Original Versão Global",
    "featured": false,
    "url": "https://shope.ee/2Ap0IEVUxO"
  },
  {
    "id": 38,
    "category": "Eletrodomésticos",
    "photo_main": "assets/id_38/photo_main.png",
    "title": "Fone De Ouvido Sem Fio Bluetooth  À Prova D'água Com Redução de Ruído",
    "featured": false,
    "url": "https://amzn.to/4awC004"
  },
  {
    "id": 39,
    "category": "Eletrodomésticos",
    "photo_main": "assets/id_39/photo_main.png",
    "title": "JBL, Caixa de Som",
    "featured": false,
    "url": "https://amzn.to/3RVemDe"
  }
]